internet_speed_package/__init__.py
internet_speed_package/datetime.py
internet_speed_package/speed.py
ghost_speed-0.1.dist-info/METADATA
ghost_speed-0.1.dist-info/WHEEL
ghost_speed-0.1.dist-info/top_level.txt
ghost_speed-0.1.dist-info/RECORD
